super_scad_prism_hedron/SmoothPrismHedron.py
super_scad_prism_hedron/__init__.py
super_scad_prism_hedron/node_smoother/BottomInnerExternalSide1NodeSmoother.py
super_scad_prism_hedron/node_smoother/BottomInnerExternalSide2NodeSmoother.py
super_scad_prism_hedron/node_smoother/BottomOuterExternalSide1NodeSmoother.py
super_scad_prism_hedron/node_smoother/BottomOuterExternalSide2NodeSmoother.py
super_scad_prism_hedron/node_smoother/BottomStarNodeSmoother.py
super_scad_prism_hedron/node_smoother/NodeSmoother.py
super_scad_prism_hedron/node_smoother/TopInnerExternalSide1NodeSmoother.py
super_scad_prism_hedron/node_smoother/TopInnerExternalSide2NodeSmoother.py
super_scad_prism_hedron/node_smoother/TopOuterExternalSide1NodeSmoother.py
super_scad_prism_hedron/node_smoother/TopOuterExternalSide2NodeSmoother.py
super_scad_prism_hedron/node_smoother/TopStarNodeSmoother.py
super_scad_prism_hedron/node_smoother/__init__.py
super_scad_prism_hedron-0.9.2.dist-info/LICENSE
super_scad_prism_hedron-0.9.2.dist-info/METADATA
super_scad_prism_hedron-0.9.2.dist-info/WHEEL
super_scad_prism_hedron-0.9.2.dist-info/RECORD
